seqikpy/__init__.py
seqikpy/alignment.py
seqikpy/data.py
seqikpy/head_inverse_kinematics.py
seqikpy/kinematic_chain.py
seqikpy/leg_inverse_kinematics.py
seqikpy/utils.py
seqikpy/visualization.py
seqikpy-1.0.3.dist-info/.DS_Store
seqikpy-1.0.3.dist-info/LICENSE.md
seqikpy-1.0.3.dist-info/METADATA
seqikpy-1.0.3.dist-info/WHEEL
seqikpy-1.0.3.dist-info/top_level.txt
seqikpy-1.0.3.dist-info/RECORD
