Metadata-Version: 2.2
Name: seqikpy
Version: 1.0.3
Summary: Inverse kinematics module for Drosophila
Home-page: https://github.com/NeLy-EPFL/sequential-inverse-kinematics.git
License: Apache License 2.0
Keywords: inverse kinematics,robotics,insects,motion analysis
Classifier: Development Status :: 4 - Beta
Classifier: Operating System :: OS Independent
Classifier: Programming Language :: Python :: 3
Classifier: License :: OSI Approved :: Apache Software License
Classifier: Topic :: Software Development :: Libraries
Requires-Python: >3.8,<3.11
License-File: LICENSE.md
Requires-Dist: ikpy>=3.3.4
Requires-Dist: opencv-python==4.5.*
Requires-Dist: numpy<2.0
Requires-Dist: tqdm
Requires-Dist: matplotlib
Requires-Dist: pandas
Provides-Extra: dev
Requires-Dist: pytest; extra == "dev"
Requires-Dist: ImageHash; extra == "dev"
Requires-Dist: black==22.3.0; extra == "dev"
Dynamic: classifier
Dynamic: description
Dynamic: description-content-type
Dynamic: home-page
Dynamic: keywords
Dynamic: license
Dynamic: provides-extra
Dynamic: requires-dist
Dynamic: requires-python
Dynamic: summary
